open_link/__init__.py
open_link/main.py
open_link/open_link.py
open_link-0.1.9.dist-info/entry_points.txt
open_link-0.1.9.dist-info/WHEEL
open_link-0.1.9.dist-info/METADATA
open_link-0.1.9.dist-info/RECORD
